pykospacing/__init__.py
pykospacing2/__init__.py
pykospacing2-0.1.0.dist-info/licenses/LICENSE
pykospacing2-0.1.0.dist-info/METADATA
pykospacing2-0.1.0.dist-info/WHEEL
pykospacing2-0.1.0.dist-info/top_level.txt
pykospacing2-0.1.0.dist-info/RECORD
